stem_rate/__about__.py
stem_rate/__init__.py
stem_rate/__main__.py
stem_rate/cli/__init__.py
stem_rate-0.0.3.dist-info/METADATA
stem_rate-0.0.3.dist-info/WHEEL
stem_rate-0.0.3.dist-info/entry_points.txt
stem_rate-0.0.3.dist-info/licenses/LICENSE.txt
stem_rate-0.0.3.dist-info/RECORD
